smk2rst/__init__.py
smk2rst/docopt.py
smk2rst/version.py
smk2rst/cli/digest_codebase.py
smk2rst-0.1.0.dist-info/LICENSE
smk2rst-0.1.0.dist-info/METADATA
smk2rst-0.1.0.dist-info/WHEEL
smk2rst-0.1.0.dist-info/entry_points.txt
smk2rst-0.1.0.dist-info/top_level.txt
smk2rst-0.1.0.dist-info/RECORD
